rigid_body_motion/__init__.py
rigid_body_motion/accessors.py
rigid_body_motion/coordinate_systems.py
rigid_body_motion/core.py
rigid_body_motion/estimators.py
rigid_body_motion/io.py
rigid_body_motion/plot.py
rigid_body_motion/plotting.py
rigid_body_motion/reference_frames.py
rigid_body_motion/testing.py
rigid_body_motion/utils.py
rigid_body_motion/ros/__init__.py
rigid_body_motion/ros/check_install.py
rigid_body_motion/ros/io.py
rigid_body_motion/ros/msg.py
rigid_body_motion/ros/transformer.py
rigid_body_motion/ros/utils.py
rigid_body_motion/ros/visualization.py
rigid_body_motion-0.9.3.dist-info/METADATA
rigid_body_motion-0.9.3.dist-info/WHEEL
rigid_body_motion-0.9.3.dist-info/licenses/AUTHORS.rst
rigid_body_motion-0.9.3.dist-info/licenses/LICENSE
rigid_body_motion-0.9.3.dist-info/RECORD
