Metadata-Version: 2.4
Name: rigid-body-motion
Version: 0.9.3
Summary: Python utilities for estimating and transforming rigid body motion.
Project-URL: Homepage, https://github.com/phausamann/rigid-body-motion
Author-email: Peter Hausamann <peter.hausamann@tum.de>
License-Expression: MIT
License-File: AUTHORS.rst
License-File: LICENSE
Keywords: rigid_body_motion
Classifier: Development Status :: 2 - Pre-Alpha
Classifier: Intended Audience :: Developers
Classifier: License :: OSI Approved :: MIT License
Classifier: Natural Language :: English
Classifier: Programming Language :: Python :: 3
Classifier: Programming Language :: Python :: 3.8
Classifier: Programming Language :: Python :: 3.9
Classifier: Programming Language :: Python :: 3.10
Classifier: Programming Language :: Python :: 3.11
Classifier: Programming Language :: Python :: 3.12
Requires-Python: >=3.8
Requires-Dist: anytree
Requires-Dist: numpy
Requires-Dist: numpy-quaternion
Requires-Dist: scipy
Provides-Extra: all
Requires-Dist: matplotlib; extra == 'all'
Requires-Dist: netcdf4; extra == 'all'
Requires-Dist: numba; extra == 'all'
Requires-Dist: pandas; extra == 'all'
Requires-Dist: pooch; extra == 'all'
Requires-Dist: xarray; extra == 'all'
